[
  {
    "id": 845936,
    "question_text": "For a hybrid car traveling a distance of $m$ miles, the amount of fuel consumed is $g$ gallons. The ratio of $m$ to $g$ can be estimated to be 55 to 1. According to this estimate, the car will travel how many miles if it consumes 3 gallons of fuel?",
    "image_url": null,
    "difficulty": "Easy",
    "subject": "Math",
    "category": "Problem-Solving and Data Analysis",
    "subcategory": "Ratios, Rates, Proportions, and Units",
    "subject_id": 1,
    "category_id": 7,
    "subcategory_id": 25
  },
  {
    "id": 167771,
    "question_text": "A bakery produced 450 cakes in a 15-hour period. On average, how many cakes were produced per hour?",
    "image_url": null,
    "difficulty": "Easy",
    "subject": "Math",
    "category": "Problem-Solving and Data Analysis",
    "subcategory": "Ratios, Rates, Proportions, and Units",
    "subject_id": 1,
    "category_id": 7,
    "subcategory_id": 25
  },
  {
    "id": 443124,
    "question_text": "In a flower vase, the ratio of roses to tulips is 4 to 7. There are 12 roses in the vase. How many tulips are in the vase?",
    "image_url": null,
    "difficulty": "Easy",
    "subject": "Math",
    "category": "Problem-Solving and Data Analysis",
    "subcategory": "Ratios, Rates, Proportions, and Units",
    "subject_id": 1,
    "category_id": 7,
    "subcategory_id": 25
  },
  {
    "id": 771256,
    "question_text": "The book density on a bookshelf in a library is 40 books per meter. A librarian needs to shelve 12,000 books. What is the required length of the bookshelf, in meters?",
    "image_url": null,
    "difficulty": "Easy",
    "subject": "Math",
    "category": "Problem-Solving and Data Analysis",
    "subcategory": "Ratios, Rates, Proportions, and Units",
    "subject_id": 1,
    "category_id": 7,
    "subcategory_id": 25
  },
  {
    "id": 777942,
    "question_text": "A student types 1,200 words in 30 minutes. At this rate, how many words per minute does the student type?",
    "image_url": null,
    "difficulty": "Easy",
    "subject": "Math",
    "category": "Problem-Solving and Data Analysis",
    "subcategory": "Ratios, Rates, Proportions, and Units",
    "subject_id": 1,
    "category_id": 7,
    "subcategory_id": 25
  },
  {
    "id": 277206,
    "question_text": "How many meters are equivalent to 3.5 kilometers? (1 kilometer = 1000 meters)",
    "image_url": null,
    "difficulty": "Easy",
    "subject": "Math",
    "category": "Problem-Solving and Data Analysis",
    "subcategory": "Ratios, Rates, Proportions, and Units",
    "subject_id": 1,
    "category_id": 7,
    "subcategory_id": 25
  },
  {
    "id": 653388,
    "question_text": "A bakery sells muffins and croissants. On a particular morning, they sold 35 muffins and 15 croissants. What is the ratio of croissants sold to muffins sold?",
    "image_url": null,
    "difficulty": "Easy",
    "subject": "Math",
    "category": "Problem-Solving and Data Analysis",
    "subcategory": "Ratios, Rates, Proportions, and Units",
    "subject_id": 1,
    "category_id": 7,
    "subcategory_id": 25
  },
  {
    "id": 103,
    "question_text": "A hummingbird is 8 centimeters long. What is the hummingbird's length, in millimeters? (1 centimeter = 10 millimeters)",
    "image_url": null,
    "difficulty": "Easy",
    "subject": "Math",
    "category": "Problem-Solving and Data Analysis",
    "subcategory": "Ratios, Rates, Proportions, and Units",
    "subject_id": 1,
    "category_id": 7,
    "subcategory_id": 25
  },
  {
    "id": 641810,
    "question_text": "How many pints are equivalent to 5 gallons? (1 gallon = 8 pints)",
    "image_url": null,
    "difficulty": "Easy",
    "subject": "Math",
    "category": "Problem-Solving and Data Analysis",
    "subcategory": "Ratios, Rates, Proportions, and Units",
    "subject_id": 1,
    "category_id": 7,
    "subcategory_id": 25
  },
  {
    "id": 230721,
    "question_text": "A car gets 30 miles per gallon of gasoline. How many quarts of gasoline are needed for the car to travel 150 miles? (1 gallon = 4 quarts)",
    "image_url": null,
    "difficulty": "Easy",
    "subject": "Math",
    "category": "Problem-Solving and Data Analysis",
    "subcategory": "Ratios, Rates, Proportions, and Units",
    "subject_id": 1,
    "category_id": 7,
    "subcategory_id": 25
  },
  {
    "id": 32498,
    "question_text": "A painter has 15 liters of paint and needs to convert it to gallons for a project. The conversion rate is approximately 1 gallon = 3.785 liters. During the transfer process, 10% of the paint is wasted due to spillage. How many gallons of paint, after accounting for the wastage, will the painter have for the project?",
    "image_url": null,
    "difficulty": "Easy",
    "subject": "Math",
    "category": "Problem-Solving and Data Analysis",
    "subcategory": "Ratios, Rates, Proportions, and Units",
    "subject_id": 1,
    "category_id": 7,
    "subcategory_id": 25
  },
  {
    "id": 181816,
    "question_text": "A baker is making cookies for a large order. Each cookie requires 2.5 ounces of dough. If the baker has 75 ounces of dough available, what is the maximum number of cookies the baker can make?",
    "image_url": null,
    "difficulty": "Easy",
    "subject": "Math",
    "category": "Problem-Solving and Data Analysis",
    "subcategory": "Ratios, Rates, Proportions, and Units",
    "subject_id": 1,
    "category_id": 7,
    "subcategory_id": 25
  },
  {
    "id": 656326,
    "question_text": "If $p = 3q$, which of the following is equivalent to $4p$?",
    "image_url": null,
    "difficulty": "Easy",
    "subject": "Math",
    "category": "Problem-Solving and Data Analysis",
    "subcategory": "Ratios, Rates, Proportions, and Units",
    "subject_id": 1,
    "category_id": 7,
    "subcategory_id": 25
  },
  {
    "id": 292708,
    "question_text": "How many fluid ounces are equivalent to 5 cups? (8 fluid ounces = 1 cup)",
    "image_url": null,
    "difficulty": "Easy",
    "subject": "Math",
    "category": "Problem-Solving and Data Analysis",
    "subcategory": "Ratios, Rates, Proportions, and Units",
    "subject_id": 1,
    "category_id": 7,
    "subcategory_id": 25
  },
  {
    "id": 206261,
    "question_text": "A student is preparing a presentation. The presentation is designed to be 540 seconds in length. How many minutes long is the presentation? (1 minute = 60 seconds)",
    "image_url": null,
    "difficulty": "Easy",
    "subject": "Math",
    "category": "Problem-Solving and Data Analysis",
    "subcategory": "Ratios, Rates, Proportions, and Units",
    "subject_id": 1,
    "category_id": 7,
    "subcategory_id": 25
  },
  {
    "id": 364635,
    "question_text": "A store sells notebooks for $2.50 each. What is the total cost, in dollars, of buying 8 notebooks?",
    "image_url": null,
    "difficulty": "Easy",
    "subject": "Math",
    "category": "Problem-Solving and Data Analysis",
    "subcategory": "Ratios, Rates, Proportions, and Units",
    "subject_id": 1,
    "category_id": 7,
    "subcategory_id": 25
  },
  {
    "id": 925604,
    "question_text": "A baker can decorate 5 cakes in 1 hour. At this rate, how many hours would it take the baker to decorate 35 cakes?",
    "image_url": null,
    "difficulty": "Easy",
    "subject": "Math",
    "category": "Problem-Solving and Data Analysis",
    "subcategory": "Ratios, Rates, Proportions, and Units",
    "subject_id": 1,
    "category_id": 7,
    "subcategory_id": 25
  },
  {
    "id": 235841,
    "question_text": "The ratio of the number of apples to the number of bananas in a fruit basket is 7 to 3. If there are 42 apples in the basket, how many bananas are in the basket?",
    "image_url": null,
    "difficulty": "Easy",
    "subject": "Math",
    "category": "Problem-Solving and Data Analysis",
    "subcategory": "Ratios, Rates, Proportions, and Units",
    "subject_id": 1,
    "category_id": 7,
    "subcategory_id": 25
  },
  {
    "id": 549107,
    "question_text": "A cheetah can run at a maximum speed of 120 kilometers per hour. What is the cheetah's maximum speed in meters per second?",
    "image_url": null,
    "difficulty": "Medium",
    "subject": "Math",
    "category": "Problem-Solving and Data Analysis",
    "subcategory": "Ratios, Rates, Proportions, and Units",
    "subject_id": 1,
    "category_id": 7,
    "subcategory_id": 25
  },
  {
    "id": 210237,
    "question_text": "The population density of Cityville, in people per square kilometer of land area, increased from 60 in 2010 to 75 in 2020. During this ten-year period, the land area of Cityville remained constant at 300 square kilometers. By how many people did Cityville's population increase from 2010 to 2020?",
    "image_url": null,
    "difficulty": "Medium",
    "subject": "Math",
    "category": "Problem-Solving and Data Analysis",
    "subcategory": "Ratios, Rates, Proportions, and Units",
    "subject_id": 1,
    "category_id": 7,
    "subcategory_id": 25
  },
  {
    "id": 717525,
    "question_text": "A car's fuel efficiency is rated at 30 miles per gallon. If the average price of gasoline is $4.50 per gallon, what is the cost of gasoline, in dollars, to drive this car one mile?",
    "image_url": null,
    "difficulty": "Medium",
    "subject": "Math",
    "category": "Problem-Solving and Data Analysis",
    "subcategory": "Ratios, Rates, Proportions, and Units",
    "subject_id": 1,
    "category_id": 7,
    "subcategory_id": 25
  },
  {
    "id": 508728,
    "question_text": "A family drove from City A to City B, a distance of 215 miles. The trip took 4 hours and 30 minutes. What was their average speed in miles per hour during this trip, rounded to the nearest whole number?",
    "image_url": null,
    "difficulty": "Medium",
    "subject": "Math",
    "category": "Problem-Solving and Data Analysis",
    "subcategory": "Ratios, Rates, Proportions, and Units",
    "subject_id": 1,
    "category_id": 7,
    "subcategory_id": 25
  },
  {
    "id": 711911,
    "question_text": "Rectangle P has a length of $x$ and a width of 6. Rectangle Q has a width of 9 and the same length-to-width ratio as rectangle P. What is the length of rectangle Q in terms of $x$?",
    "image_url": null,
    "difficulty": "Medium",
    "subject": "Math",
    "category": "Problem-Solving and Data Analysis",
    "subcategory": "Ratios, Rates, Proportions, and Units",
    "subject_id": 1,
    "category_id": 7,
    "subcategory_id": 25
  },
  {
    "id": 237924,
    "question_text": "A train travels at a constant speed of 55 miles per hour. If the train travels for $z$ hours, it covers a distance of $55z$ miles. Which of the following expressions gives the distance, in miles, the train will travel if it travels for $\frac{z}{2}$ hours?",
    "image_url": null,
    "difficulty": "Medium",
    "subject": "Math",
    "category": "Problem-Solving and Data Analysis",
    "subcategory": "Ratios, Rates, Proportions, and Units",
    "subject_id": 1,
    "category_id": 7,
    "subcategory_id": 25
  },
  {
    "id": 952753,
    "question_text": "A recipe for fruit punch requires 2 cups of orange juice per serving.  Maria is making a large batch of fruit punch for a school event and has 3 gallons of orange juice. How many full servings of fruit punch can Maria make? (1 gallon = 16 cups)",
    "image_url": null,
    "difficulty": "Medium",
    "subject": "Math",
    "category": "Problem-Solving and Data Analysis",
    "subcategory": "Ratios, Rates, Proportions, and Units",
    "subject_id": 1,
    "category_id": 7,
    "subcategory_id": 25
  },
  {
    "id": 557444,
    "question_text": "A delivery truck uses 16 gallons of fuel for each delivery route it completes. A larger delivery truck uses 18 gallons of fuel for each delivery route it completes. How many more gallons of fuel does the larger delivery truck use than the smaller delivery truck if each truck completes 32 delivery routes?",
    "image_url": null,
    "difficulty": "Medium",
    "subject": "Math",
    "category": "Problem-Solving and Data Analysis",
    "subcategory": "Ratios, Rates, Proportions, and Units",
    "subject_id": 1,
    "category_id": 7,
    "subcategory_id": 25
  },
  {
    "id": 752598,
    "question_text": "A cheetah is running at a speed of 30 miles per hour. Which of the following is equivalent to this speed in feet per second? (1 mile = 5,280 feet)",
    "image_url": null,
    "difficulty": "Medium",
    "subject": "Math",
    "category": "Problem-Solving and Data Analysis",
    "subcategory": "Ratios, Rates, Proportions, and Units",
    "subject_id": 1,
    "category_id": 7,
    "subcategory_id": 25
  },
  {
    "id": 558987,
    "question_text": "A container holds 5 gallons of juice. How many milliliters of juice are in the container? (1 gallon = 4 liters and 1 liter = 1000 milliliters)",
    "image_url": null,
    "difficulty": "Medium",
    "subject": "Math",
    "category": "Problem-Solving and Data Analysis",
    "subcategory": "Ratios, Rates, Proportions, and Units",
    "subject_id": 1,
    "category_id": 7,
    "subcategory_id": 25
  },
  {
    "id": 810054,
    "question_text": "A car has a fuel efficiency of 32 miles per gallon. If the car used 12.5 gallons of fuel on a trip, how far, in miles, did the car travel?",
    "image_url": null,
    "difficulty": "Medium",
    "subject": "Math",
    "category": "Problem-Solving and Data Analysis",
    "subcategory": "Ratios, Rates, Proportions, and Units",
    "subject_id": 1,
    "category_id": 7,
    "subcategory_id": 25
  },
  {
    "id": 555498,
    "question_text": "A recipe calls for 5 gallons of water. If 1 gallon is equal to 4 quarts, 1 quart is equal to 2 pints, 1 pint is equal to 2 cups, and 1 cup is equal to 8 fluid ounces, then 5 gallons is equivalent to how many fluid ounces?",
    "image_url": null,
    "difficulty": "Medium",
    "subject": "Math",
    "category": "Problem-Solving and Data Analysis",
    "subcategory": "Ratios, Rates, Proportions, and Units",
    "subject_id": 1,
    "category_id": 7,
    "subcategory_id": 25
  },
  {
    "id": 948954,
    "question_text": "In a recipe for cookies, the ratio of cups of flour to cups of sugar is 5 to 2. If a baker decides to use 2.5 times the amount of flour for a larger batch, by what factor should they multiply the amount of sugar to maintain the same recipe ratio?",
    "image_url": null,
    "difficulty": "Medium",
    "subject": "Math",
    "category": "Problem-Solving and Data Analysis",
    "subcategory": "Ratios, Rates, Proportions, and Units",
    "subject_id": 1,
    "category_id": 7,
    "subcategory_id": 25
  },
  {
    "id": 743561,
    "question_text": "A carpenter is building a bookshelf. The design specifies that each shelf should be 2.5 feet long. How many inches long should each shelf be? (1 foot = 12 inches)",
    "image_url": null,
    "difficulty": "Medium",
    "subject": "Math",
    "category": "Problem-Solving and Data Analysis",
    "subcategory": "Ratios, Rates, Proportions, and Units",
    "subject_id": 1,
    "category_id": 7,
    "subcategory_id": 25
  },
  {
    "id": 928391,
    "question_text": "A runner completed a race at an average speed of 0.3 kilometers per minute. What was the average speed, in meters per second, of the runner during the race? (1 kilometer = 1,000 meters, 1 minute = 60 seconds)",
    "image_url": null,
    "difficulty": "Medium",
    "subject": "Math",
    "category": "Problem-Solving and Data Analysis",
    "subcategory": "Ratios, Rates, Proportions, and Units",
    "subject_id": 1,
    "category_id": 7,
    "subcategory_id": 25
  },
  {
    "id": 654624,
    "question_text": "A school district's total budget is $48.5 million, of which $12.8 million is allocated to administrative costs. If the district serves 8,200 students, which of the following is closest to the amount of money spent per student on non-administrative costs?",
    "image_url": null,
    "difficulty": "Medium",
    "subject": "Math",
    "category": "Problem-Solving and Data Analysis",
    "subcategory": "Ratios, Rates, Proportions, and Units",
    "subject_id": 1,
    "category_id": 7,
    "subcategory_id": 25
  },
  {
    "id": 506328,
    "question_text": "$$$C = 25n$  The equation above can be used to calculate the cost $C, in dollars, of purchasing n notebooks at a price of $25 per notebook. For any positive constant p, the cost of purchasing 12p notebooks is how many times the cost of purchasing 3p notebooks?",
    "image_url": null,
    "difficulty": "Medium",
    "subject": "Math",
    "category": "Problem-Solving and Data Analysis",
    "subcategory": "Ratios, Rates, Proportions, and Units",
    "subject_id": 1,
    "category_id": 7,
    "subcategory_id": 25
  },
  {
    "id": 137990,
    "question_text": "How many inches are equivalent to 3 miles? (1 mile = 5280 feet and 1 foot = 12 inches)",
    "image_url": null,
    "difficulty": "Medium",
    "subject": "Math",
    "category": "Problem-Solving and Data Analysis",
    "subcategory": "Ratios, Rates, Proportions, and Units",
    "subject_id": 1,
    "category_id": 7,
    "subcategory_id": 25
  },
  {
    "id": 34867,
    "question_text": "A grocery store sells honey in large jars. A jar contains 3 pints of honey and costs $12. What is the price of the honey per fluid ounce? (1 pint = 16 fluid ounces)",
    "image_url": null,
    "difficulty": "Medium",
    "subject": "Math",
    "category": "Problem-Solving and Data Analysis",
    "subcategory": "Ratios, Rates, Proportions, and Units",
    "subject_id": 1,
    "category_id": 7,
    "subcategory_id": 25
  },
  {
    "id": 26783,
    "question_text": "The ratio of 15 to $x$ is equivalent to the ratio of 3 to 12. What is the value of $x$?",
    "image_url": null,
    "difficulty": "Medium",
    "subject": "Math",
    "category": "Problem-Solving and Data Analysis",
    "subcategory": "Ratios, Rates, Proportions, and Units",
    "subject_id": 1,
    "category_id": 7,
    "subcategory_id": 25
  },
  {
    "id": 314416,
    "question_text": "One method of calculating the approximate age, in years, of a tree of a particular species is to multiply the diameter of the tree, in inches, by a constant called the growth factor for that species. The table above gives the growth factors for eight species of trees. A White Birch tree currently has a diameter of 10 inches and a Pin Oak tree currently has a diameter of 15 inches. Which of the following will be closest to the difference, in inches, of their diameters 10 years from now?",
    "image_url": "null",
    "difficulty": "Hard",
    "subject": "Math",
    "category": "Problem-Solving and Data Analysis",
    "subcategory": "Ratios, Rates, Proportions, and Units",
    "subject_id": 1,
    "category_id": 7,
    "subcategory_id": 25
  },
  {
    "id": 78055,
    "question_text": "A biologist starts an experiment with a colony of bacteria. The number of bacteria triples every hour. After 3 hours, there are 8,100 bacteria in the colony. How many bacteria were there at the start of the experiment?",
    "image_url": null,
    "difficulty": "Hard",
    "subject": "Math",
    "category": "Problem-Solving and Data Analysis",
    "subcategory": "Ratios, Rates, Proportions, and Units",
    "subject_id": 1,
    "category_id": 7,
    "subcategory_id": 25
  },
  {
    "id": 13531,
    "question_text": "The table shows the daily water usage rate per acre and the number of acres planted for three different agricultural regions.  | Region   | Water Usage Rate (Gallons per Acre per Day) | Acres Planted | |----------|---------------------------------------------|----------------| | Region A | 500                                         | 100            | | Region B | 600                                         | 150            | | Region C | 400                                         | 200            |  If all regions maintain these water usage rates, what is the total water usage, in gallons, for Region B in a week (7 days)?",
    "image_url": null,
    "difficulty": "Hard",
    "subject": "Math",
    "category": "Problem-Solving and Data Analysis",
    "subcategory": "Ratios, Rates, Proportions, and Units",
    "subject_id": 1,
    "category_id": 7,
    "subcategory_id": 25
  },
  {
    "id": 600669,
    "question_text": "If $\\frac{\\Psi}{\\Omega} = 2.5$ and $\\frac{\\Phi}{\\Omega} = 7.5$, what is the value of $n = \\frac{\\Psi}{\\Phi}$?",
    "image_url": null,
    "difficulty": "Hard",
    "subject": "Math",
    "category": "Problem-Solving and Data Analysis",
    "subcategory": "Ratios, Rates, Proportions, and Units",
    "subject_id": 1,
    "category_id": 7,
    "subcategory_id": 25
  },
  {
    "id": 703590,
    "question_text": "The density of gold is approximately 19,300 kilograms per cubic meter. A sample of pure gold is in the shape of a cube and has a mass of 25 kilograms. To the nearest hundredth of a meter, what is the length of one edge of this sample?",
    "image_url": null,
    "difficulty": "Hard",
    "subject": "Math",
    "category": "Problem-Solving and Data Analysis",
    "subcategory": "Ratios, Rates, Proportions, and Units",
    "subject_id": 1,
    "category_id": 7,
    "subcategory_id": 25
  },
  {
    "id": 313002,
    "question_text": "A gardener is preparing a fertilizer mixture by combining nitrogen and phosphorus in a ratio of 5 parts nitrogen to 2 parts phosphorus. For a large batch, the gardener wants to use 12.5 pounds of nitrogen, while maintaining the same ratio. How many pounds of phosphorus should the gardener use?",
    "image_url": null,
    "difficulty": "Hard",
    "subject": "Math",
    "category": "Problem-Solving and Data Analysis",
    "subcategory": "Ratios, Rates, Proportions, and Units",
    "subject_id": 1,
    "category_id": 7,
    "subcategory_id": 25
  },
  {
    "id": 643351,
    "question_text": "A jewelry maker is crafting pendants using pure gold. She melts gold and pours it into cubic molds. One such mold has an edge length of 2.00 centimeters. Pure gold has a density of 19.3 grams per cubic centimeter. What is the mass, in grams, of a gold pendant made using this mold, assuming the mold is filled completely?",
    "image_url": null,
    "difficulty": "Hard",
    "subject": "Math",
    "category": "Problem-Solving and Data Analysis",
    "subcategory": "Ratios, Rates, Proportions, and Units",
    "subject_id": 1,
    "category_id": 7,
    "subcategory_id": 25
  }
]